stadiamaps/__init__.py
stadiamaps/api_client.py
stadiamaps/api_response.py
stadiamaps/configuration.py
stadiamaps/exceptions.py
stadiamaps/py.typed
stadiamaps/rest.py
stadiamaps/api/__init__.py
stadiamaps/api/geocoding_api.py
stadiamaps/api/geospatial_api.py
stadiamaps/api/routing_api.py
stadiamaps/models/__init__.py
stadiamaps/models/access.py
stadiamaps/models/addendum_v2.py
stadiamaps/models/address_components_v2.py
stadiamaps/models/admin_region.py
stadiamaps/models/administrative.py
stadiamaps/models/annotation_filters.py
stadiamaps/models/auto_costing_options.py
stadiamaps/models/auto_costing_options_all_of.py
stadiamaps/models/base_costing_options.py
stadiamaps/models/base_trace_request.py
stadiamaps/models/bicycle_costing_options.py
stadiamaps/models/bicycle_costing_options_all_of.py
stadiamaps/models/bike_network.py
stadiamaps/models/bulk_request.py
stadiamaps/models/bulk_request_query.py
stadiamaps/models/bulk_search_request_inner.py
stadiamaps/models/bulk_search_response.py
stadiamaps/models/context.py
stadiamaps/models/contour.py
stadiamaps/models/coordinate.py
stadiamaps/models/costing_model.py
stadiamaps/models/costing_options.py
stadiamaps/models/directions_options.py
stadiamaps/models/distance_unit.py
stadiamaps/models/edge_sign.py
stadiamaps/models/edge_use.py
stadiamaps/models/end_node.py
stadiamaps/models/extended_directions_options.py
stadiamaps/models/feature_properties_v2.py
stadiamaps/models/feature_properties_v2_properties.py
stadiamaps/models/foursquare_addendum.py
stadiamaps/models/geo_attributes.py
stadiamaps/models/geo_json_geometry.py
stadiamaps/models/geo_json_geometry_base.py
stadiamaps/models/geo_json_line_string.py
stadiamaps/models/geo_json_line_string_all_of.py
stadiamaps/models/geo_json_point.py
stadiamaps/models/geo_json_point_all_of.py
stadiamaps/models/geo_json_polygon.py
stadiamaps/models/geo_json_polygon_all_of.py
stadiamaps/models/geocode_response.py
stadiamaps/models/geocode_response_envelope_properties_v2.py
stadiamaps-7.0.1.dist-info/licenses/LICENSE.txt
stadiamaps-7.0.1.dist-info/METADATA
stadiamaps-7.0.1.dist-info/WHEEL
stadiamaps-7.0.1.dist-info/top_level.txt
stadiamaps-7.0.1.dist-info/RECORD
