Metadata-Version: 2.4
Name: stadiamaps
Version: 7.0.1
Summary: Stadia Maps Geospatial APIs
Author-email: Stadia Maps Support <support@stadiamaps.com>
License-Expression: BSD-3-Clause
Project-URL: homepage, https://stadiamaps.com
Project-URL: documentation, https://docs.stadiamaps.com/sdks/python/
Project-URL: source, https://github.com/stadiamaps/stadiamaps-api-py
Requires-Python: >=3.8
License-File: LICENSE.txt
Requires-Dist: urllib3<3.0.0,>=1.25.3
Requires-Dist: python-dateutil>=2.8.2
Requires-Dist: pydantic>=2
Requires-Dist: typing-extensions>=4.7.1
Dynamic: license-file
